estnltk/__init__.py
estnltk/core.py
estnltk/text.py
estnltk/converters/__init__.py
estnltk/converters/dict_exporter.py
estnltk/converters/dict_importer.py
estnltk/converters/json_converter.py
estnltk/converters/json_exporter.py
estnltk/converters/json_importer.py
estnltk/converters/layer_dict_converter.py
estnltk/converters/serialisation_modules/__init__.py
estnltk/converters/serialisation_modules/default.py
estnltk/converters/serialisation_modules/legacy_v0.py
estnltk/converters/serialisation_modules/serialisation_map.py
estnltk/converters/serialisation_modules/syntax_v0.py
estnltk/layer/__init__.py
estnltk/layer/ambiguous_attribute_list.py
estnltk/layer/ambiguous_attribute_tuple_list.py
estnltk/layer/annotation.py
estnltk/layer/attribute_list.py
estnltk/layer/attribute_tuple_list.py
estnltk/layer/base_span.py
estnltk/layer/enveloping_span.py
estnltk/layer/immutable_list.py
estnltk/layer/layer.py
estnltk/layer/span.py
estnltk/layer/span_list.py
estnltk/layer/span_operations.py
estnltk/layer_operations/__init__.py
estnltk/layer_operations/combine.py
estnltk/layer_operations/conflict_resolver.py
estnltk/layer_operations/consecutive.py
estnltk/layer_operations/flatten.py
estnltk/layer_operations/groupby.py
estnltk/layer_operations/intersections.py
estnltk/layer_operations/layer_indexing.py
estnltk/layer_operations/layer_operations.py
estnltk/layer_operations/merge.py
estnltk/layer_operations/rebase.py
estnltk/layer_operations/rolling.py
estnltk/layer_operations/splitting.py
estnltk/layer_operations/splitting_discontinuous.py
estnltk/taggers/__init__.py
estnltk/taggers/retagger.py
estnltk/taggers/tagger.py
estnltk_light-1.6.7.7b0.dist-info/LICENSE
estnltk_light-1.6.7.7b0.dist-info/METADATA
estnltk_light-1.6.7.7b0.dist-info/WHEEL
estnltk_light-1.6.7.7b0.dist-info/top_level.txt
estnltk_light-1.6.7.7b0.dist-info/RECORD
