Metadata-Version: 2.1
Name: estnltk-light
Version: 1.6.7.7b0
Summary: EstNLTK light — core components of the EstNLTK v1.6 library
Home-page: https://github.com/estnltk/estnltk
Author: University of Tartu
Author-email: siim.orasmaa@gmail.com, alex.tk.fb@gmail.com, tpetmanson@gmail.com, swen@math.ut.ee
License: GPLv2
Classifier: Intended Audience :: Developers
Classifier: Intended Audience :: Education
Classifier: Intended Audience :: Science/Research
Classifier: Intended Audience :: Information Technology
Classifier: Operating System :: OS Independent
Classifier: Programming Language :: Python :: 3.6
Classifier: Programming Language :: Python :: 3.7
Classifier: Programming Language :: Python :: 3.8
Classifier: Topic :: Scientific/Engineering
Classifier: Topic :: Scientific/Engineering :: Artificial Intelligence
Classifier: Topic :: Scientific/Engineering :: Information Analysis
Classifier: Topic :: Text Processing
Classifier: Topic :: Text Processing :: Linguistic
License-File: LICENSE
Requires-Dist: networkx
